POPSRegression/POPSRegression.py
POPSRegression/__init__.py
POPSRegression-0.3.4.dist-info/LICENSE
POPSRegression-0.3.4.dist-info/METADATA
POPSRegression-0.3.4.dist-info/WHEEL
POPSRegression-0.3.4.dist-info/top_level.txt
POPSRegression-0.3.4.dist-info/RECORD
