Metadata-Version: 2.2
Name: POPSRegression
Version: 0.3.4
Summary: Bayesian regression for low-noise data using POPS algorithm
Author-email: Thomas D Swinburne <thomas.swinburne@cnrs.fr>, Danny Perez <danny_perez@lanl.gov>
License: MIT
Project-URL: Homepage, https://github.com/tomswinburne/POPS-Regression
Project-URL: Bug Tracker, https://github.com/tomswinburne/POPS-Regression/issues
Project-URL: Documentation, https://github.com/tomswinburne/POPS-Regression/blob/main/README.md
Requires-Python: >=3.10
License-File: LICENSE
Requires-Dist: scikit-learn>=1.6.1
Requires-Dist: scipy>=1.6.0
Requires-Dist: numpy>=1.20.0
